intron/__about__.py
intron/__init__.py
intron/intronCounter_v2_stranded.py
intron/make_conserved_gtf.py
intron/make_conserved_intron_gtf.py
intron-0.1.0.dist-info/LICENSE
intron-0.1.0.dist-info/METADATA
intron-0.1.0.dist-info/WHEEL
intron-0.1.0.dist-info/top_level.txt
intron-0.1.0.dist-info/RECORD
